github_repo_manager-1.1.0.data/data/CHANGELOG.md
github_repo_manager-1.1.0.data/data/LICENSE
github_repo_manager-1.1.0.data/data/README.md
github_repo_manager-1.1.0.data/data/requirements.txt
repo_manager/__init__.py
repo_manager/_util.py
repo_manager/exceptions.py
repo_manager/_groups/__init__.py
repo_manager/_groups/branches.py
repo_manager/_groups/collaborators.py
repo_manager/_groups/labels.py
repo_manager/_groups/milestones.py
repo_manager/_groups/repository.py
repo_manager/_groups/teams.py
github_repo_manager-1.1.0.dist-info/LICENSE
github_repo_manager-1.1.0.dist-info/METADATA
github_repo_manager-1.1.0.dist-info/WHEEL
github_repo_manager-1.1.0.dist-info/entry_points.txt
github_repo_manager-1.1.0.dist-info/top_level.txt
github_repo_manager-1.1.0.dist-info/RECORD
