Metadata-Version: 2.1
Name: github-repo-manager
Version: 1.1.0
Summary: repo-manager
Home-page: https://github.com/mattsb42/repo-manager
Author: Matt Bullock
Author-email: m@ttsb42.com
Maintainer: Matt Bullock
License: Apache 2.0
Keywords: repo-manager repo_manager
Platform: UNKNOWN
Classifier: Development Status :: 5 - Production/Stable
Classifier: Intended Audience :: Developers
Classifier: Natural Language :: English
Classifier: License :: OSI Approved :: Apache Software License
Classifier: Programming Language :: Python
Classifier: Programming Language :: Python :: 3
Classifier: Programming Language :: Python :: 3.7
Classifier: Programming Language :: Python :: 3.8
Classifier: Programming Language :: Python :: Implementation :: CPython
Requires-Dist: PyGithub (>=1.45)
Requires-Dist: pyyaml (>=5.3)
Requires-Dist: agithub (>=2.2.2)
